multipers/__init__.py
multipers/_signed_measure_meta.py
multipers/_slicer_meta.py
multipers/distances.py
multipers/filtration_conversions.pxd
multipers/filtration_conversions.pxd.tp
multipers/filtrations.pxd
multipers/filtrations.pxd.tp
multipers/function_rips.cpython-311-darwin.so
multipers/function_rips.pyx
multipers/grids.cpython-311-darwin.so
multipers/grids.pyx
multipers/io.cpython-311-darwin.so
multipers/io.pyx
multipers/mma_structures.cpython-311-darwin.so
multipers/mma_structures.pxd
multipers/mma_structures.pyx
multipers/mma_structures.pyx.tp
multipers/multiparameter_edge_collapse.py
multipers/multiparameter_module_approximation.cpython-311-darwin.so
multipers/multiparameter_module_approximation.pyx
multipers/ops.cpython-311-darwin.so
multipers/ops.pyx
multipers/pickle.py
multipers/plots.py
multipers/point_measure.cpython-311-darwin.so
multipers/point_measure.pyx
multipers/simplex_tree_multi.cpython-311-darwin.so
multipers/simplex_tree_multi.pxd
multipers/simplex_tree_multi.pyx
multipers/simplex_tree_multi.pyx.tp
multipers/slicer.cpython-311-darwin.so
multipers/slicer.pxd
multipers/slicer.pxd.tp
multipers/slicer.pyx
multipers/slicer.pyx.tp
multipers/tensor.pxd
multipers/test.pyx
multipers/vector_interface.pxd
multipers/array_api/__init__.py
multipers/array_api/numpy.py
multipers/array_api/torch.py
multipers/data/MOL2.py
multipers/data/UCR.py
multipers/data/__init__.py
multipers/data/graphs.py
multipers/data/immuno_regions.py
multipers/data/minimal_presentation_to_st_bf.py
multipers/data/pytorch2simplextree.py
multipers/data/shape3d.py
multipers/data/synthetic.py
multipers/filtrations/__init__.py
multipers/filtrations/density.py
multipers/filtrations/filtrations.py
multipers/gudhi/Persistence_slices_interface.h
multipers/gudhi/Simplex_tree_interface.h
multipers/gudhi/Simplex_tree_multi_interface.h
multipers/gudhi/gudhi/Bitmap_cubical_complex.h
multipers/gudhi/gudhi/Bitmap_cubical_complex_base.h
multipers-2.4.1.dist-info/licenses/LICENSE
multipers-2.4.1.dist-info/METADATA
multipers-2.4.1.dist-info/WHEEL
multipers-2.4.1.dist-info/top_level.txt
multipers-2.4.1.dist-info/RECORD
