Metadata-Version: 2.4
Name: multipers
Version: 2.4.1
Summary: Multiparameter Topological Persistence for Machine Learning
Author-email: David Loiseaux <david.lapous@proton.me>, Hannah Schreiber <hannah.schreiber@inria.fr>
Maintainer-email: David Loiseaux <david.lapous@proton.me>
License-Expression: MIT
Project-URL: source, https://github.com/DavidLapous/multipers
Project-URL: download, https://pypi.org/project/multipers/#files
Project-URL: tracker, https://github.com/DavidLapous/multipers/issues
Project-URL: release notes, https://github.com/DavidLapous/multipers/releases
Keywords: TDA,Persistence,Multiparameter,sklearn,autodiff
Classifier: Development Status :: 5 - Production/Stable
Classifier: Programming Language :: Python :: 3.10
Classifier: Programming Language :: Python :: 3.11
Classifier: Programming Language :: Python :: 3.12
Classifier: Programming Language :: Python :: 3.13
Classifier: Programming Language :: Python :: 3.14
Classifier: Programming Language :: Python :: Implementation :: CPython
Classifier: Topic :: Scientific/Engineering :: Artificial Intelligence
Classifier: Topic :: Scientific/Engineering :: Mathematics
Classifier: Topic :: Scientific/Engineering :: Visualization
Classifier: Topic :: Software Development :: Libraries :: Python Modules
Requires-Python: >=3.10
License-File: LICENSE
Requires-Dist: numpy
Requires-Dist: gudhi>=3.8
Requires-Dist: tqdm
Requires-Dist: scipy
Requires-Dist: joblib
Requires-Dist: matplotlib
Requires-Dist: scikit-learn
Requires-Dist: filtration-domination
Requires-Dist: pykeops
Requires-Dist: pot
Dynamic: license-file
